core/__init__.py
core/creator.py
smithit-0.1.1.dist-info/LICENSE
smithit-0.1.1.dist-info/METADATA
smithit-0.1.1.dist-info/WHEEL
smithit-0.1.1.dist-info/entry_points.txt
smithit-0.1.1.dist-info/RECORD
