Metadata-Version: 2.1
Name: smithit
Version: 0.1.1
Summary: Forge your project structure like a blacksmith.
Author: felixLandlord
Author-email: felix.landlord.nunoo@gmail.com
Requires-Python: >=3.8
Classifier: Programming Language :: Python :: 3
Classifier: Programming Language :: Python :: 3.8
Classifier: Programming Language :: Python :: 3.9
Classifier: Programming Language :: Python :: 3.10
Classifier: Programming Language :: Python :: 3.11
Classifier: Programming Language :: Python :: 3.12
Requires-Dist: PyYAML (>=6.0.2,<7.0.0)
Requires-Dist: rich (>=13.8.1,<14.0.0)
Requires-Dist: tqdm (>=4.66.5,<5.0.0)
Requires-Dist: typer (>=0.12.5,<0.13.0)
